data.csv
jisx0402.py
jisx0402-0.1.3.dist-info/WHEEL
jisx0402-0.1.3.dist-info/METADATA
jisx0402-0.1.3.dist-info/RECORD
