Metadata-Version: 2.1
Name: jisx0402
Version: 0.1.3
Summary: 全国地方公共団体コードを扱うライブラリ.
Home-page: https://github.com/kitagawa-hr/JIS_X_0402_py
Author: kitagawa-hr
Author-email: kitagawa@cancerscan.jp
Requires-Python: >=3.6,<4.0
Classifier: Programming Language :: Python :: 3
Classifier: Programming Language :: Python :: 3.6
Classifier: Programming Language :: Python :: 3.7
Classifier: Programming Language :: Python :: 3.8
Requires-Dist: pydantic (>=1.6.1,<2.0.0)
Project-URL: Repository, https://github.com/kitagawa-hr/JIS_X_0402_py
